saltstack_vulcan-0.1.5.data/scripts/vulcan
vulcan/__init__.py
vulcan/cli.py
vulcan/config.py
vulcan/formula.py
vulcan/util.py
saltstack_vulcan-0.1.5.dist-info/LICENSE
saltstack_vulcan-0.1.5.dist-info/METADATA
saltstack_vulcan-0.1.5.dist-info/WHEEL
saltstack_vulcan-0.1.5.dist-info/top_level.txt
saltstack_vulcan-0.1.5.dist-info/RECORD
