Metadata-Version: 2.1
Name: saltstack-vulcan
Version: 0.1.5
Summary: Formula build tool for SaltStack.
Home-page: https://github.com/iamseth/saltstack-vulcan
Author: Seth Miller
Author-email: seth@sethmiller.me
License: UNKNOWN
Keywords: vulcan,salt,saltstack
Platform: UNKNOWN
Requires-Dist: GitPython (>=2.1.3)
Requires-Dist: PyYAML (>=3.12)
Requires-Dist: click (>=6.7)
